bigquery101/__init__.py
bigquery101/py.typed
bigquery101-0.1.0.dist-info/METADATA
bigquery101-0.1.0.dist-info/WHEEL
bigquery101-0.1.0.dist-info/licenses/LICENSE
bigquery101-0.1.0.dist-info/RECORD
